dash_image_gallery/DashImageGallery.py
dash_image_gallery/__init__.py
dash_image_gallery/_imports_.py
dash_image_gallery/dash_image_gallery.min.js
dash_image_gallery/dash_image_gallery.min.js.map
dash_image_gallery/metadata.json
dash_image_gallery/package-info.json
dash_image_gallery-0.0.1.dist-info/LICENSE
dash_image_gallery-0.0.1.dist-info/METADATA
dash_image_gallery-0.0.1.dist-info/WHEEL
dash_image_gallery-0.0.1.dist-info/top_level.txt
dash_image_gallery-0.0.1.dist-info/RECORD
