Metadata-Version: 2.1
Name: dash-image-gallery
Version: 0.0.1
Summary: image gallery for dash
Author: pip install python <pipinstallpython@gmail.com>
License: MIT
Classifier: Framework :: Dash
License-File: LICENSE
